cbl_migrator/__init__.py
cbl_migrator/conv.py
cbl_migrator/logs.py
cbl_migrator/migrator.py
cbl_migrator/bin/__init__.py
cbl_migrator/bin/run_migrator.py
cbl_migrator-0.5.0.dist-info/LICENSE
cbl_migrator-0.5.0.dist-info/METADATA
cbl_migrator-0.5.0.dist-info/WHEEL
cbl_migrator-0.5.0.dist-info/entry_points.txt
cbl_migrator-0.5.0.dist-info/top_level.txt
cbl_migrator-0.5.0.dist-info/RECORD
