Metadata-Version: 2.2
Name: cbl_migrator
Version: 0.5.0
Summary: Migrates Oracle dbs to PostgreSQL, MySQL and SQLite
Author-email: Eloy Félix <efelix@ebi.ac.uk>
License: MIT
Project-URL: Homepage, https://github.com/chembl/cbl_migrator
Classifier: Intended Audience :: Developers
Classifier: License :: OSI Approved :: MIT License
Classifier: Programming Language :: Python :: 3.9
Classifier: Programming Language :: Python :: 3.10
Classifier: Programming Language :: Python :: 3.11
Classifier: Programming Language :: Python :: 3.12
Classifier: Programming Language :: Python :: 3.13
License-File: LICENSE
Requires-Dist: SQLAlchemy~=2.0
Provides-Extra: test
Requires-Dist: pytest; extra == "test"
